xmlunittest.py
xmlunittest-1.0.1.dist-info/LICENSE
xmlunittest-1.0.1.dist-info/METADATA
xmlunittest-1.0.1.dist-info/WHEEL
xmlunittest-1.0.1.dist-info/top_level.txt
xmlunittest-1.0.1.dist-info/RECORD
