Metadata-Version: 2.1
Name: xmlunittest
Version: 1.0.1
Summary: Library using lxml and unittest for unit testing XML.
Author: Florian Strzelecki
Maintainer: Florian Strzelecki
License: MIT
Project-URL: Bug Tracker, https://github.com/Exirel/python-xmlunittest/issues
Project-URL: Source, https://github.com/Exirel/python-xmlunittest
Classifier: Development Status :: 5 - Production/Stable
Classifier: Framework :: Pytest
Classifier: Intended Audience :: Developers
Classifier: License :: OSI Approved :: MIT License
Classifier: Operating System :: OS Independent
Classifier: Programming Language :: Python :: 3.8
Classifier: Programming Language :: Python :: 3.9
Classifier: Programming Language :: Python :: 3.10
Classifier: Programming Language :: Python :: 3.11
Classifier: Programming Language :: Python :: 3.12
Classifier: Topic :: Software Development :: Quality Assurance
Classifier: Topic :: Software Development :: Testing
Classifier: Topic :: Software Development :: Testing :: Unit
Classifier: Topic :: Text Processing :: Markup :: XML
Requires-Python: >=3.8
License-File: LICENSE
Requires-Dist: lxml >=4.0
